weixin_work_reborn/__init__.py
weixin_work_reborn/client.py
weixin_work_reborn/common.py
weixin_work_reborn/config.py
weixin_work_reborn/exceptions.py
weixin_work_reborn/user.py
weixin_work_reborn-0.1.1.dist-info/licenses/LICENSE
weixin_work_reborn-0.1.1.dist-info/METADATA
weixin_work_reborn-0.1.1.dist-info/WHEEL
weixin_work_reborn-0.1.1.dist-info/top_level.txt
weixin_work_reborn-0.1.1.dist-info/RECORD
