Metadata-Version: 2.4
Name: weixin-work-reborn
Version: 0.1.1
Summary: A Python SDK for WeChat Work API
Author-email: Your Name <your.email@example.com>
License: MIT
Project-URL: Homepage, https://github.com/liudonghua123/weixin-work
Project-URL: Repository, https://github.com/liudonghua123/weixin-work
Project-URL: Documentation, https://github.com/liudonghua123/weixin-work#readme
Project-URL: Changelog, https://github.com/liudonghua123/weixin-work/releases
Keywords: weixin,work,wechat,api,sdk
Classifier: Development Status :: 4 - Beta
Classifier: Intended Audience :: Developers
Classifier: License :: OSI Approved :: MIT License
Classifier: Programming Language :: Python :: 3
Classifier: Programming Language :: Python :: 3.8
Classifier: Programming Language :: Python :: 3.9
Classifier: Programming Language :: Python :: 3.10
Classifier: Programming Language :: Python :: 3.11
Classifier: Programming Language :: Python :: 3.12
License-File: LICENSE
Requires-Dist: requests>=2.25.0
Requires-Dist: cachetools>=5.0.0
Requires-Dist: python-dotenv>=1.0.0
Provides-Extra: dev
Requires-Dist: pytest>=7.0.0; extra == "dev"
Requires-Dist: pytest-cov>=4.0.0; extra == "dev"
Requires-Dist: black>=22.0.0; extra == "dev"
Requires-Dist: flake8>=4.0.0; extra == "dev"
Requires-Dist: mypy>=0.950; extra == "dev"
Dynamic: license-file
